{
  "$schema": "https://developer.microsoft.com/json-schemas/spfx-build/package-solution.schema.json",
  "solution": {
    "name": "newtest-client-side-solution",
    "id": "9f3b6ecd-990d-4c45-bf01-a6ea9ed1404e",
    "version": "1.0.0.0",
    "includeClientSideAssets": true,
    "skipFeatureDeployment": true,
    "isDomainIsolated": false,
    "developer": {
      "name": "",
      "websiteUrl": "",
      "privacyUrl": "",
      "termsOfUseUrl": "",
      "mpnId": "Undefined-1.13.1"
    }
  },
  "paths": {
    "zippedPackage": "solution/newtest.sppkg"
  }
}
